[
{
  "name":"com.fasterxml.jackson.databind.ext.Java7HandlersImpl",
  "methods":[{"name":"<init>","parameterTypes":[] }]
},
{
  "name":"com.fasterxml.jackson.databind.ext.Java7SupportImpl",
  "methods":[{"name":"<init>","parameterTypes":[] }]
},
{
  "name":"com.intellij.rt.execution.application.AppMainV2$Agent",
  "methods":[{"name":"premain","parameterTypes":["java.lang.String","java.lang.instrument.Instrumentation"] }]
},
{
  "name":"com.itextpdf.kernel.pdf.PdfName",
  "allDeclaredFields":true
},
{
  "name":"java.lang.Class",
  "methods":[{"name":"getRecordComponents","parameterTypes":[] }]
},
{
  "name":"java.lang.Record",
  "allDeclaredFields":true,
  "queryAllDeclaredMethods":true
},
{
  "name":"java.lang.reflect.RecordComponent",
  "methods":[{"name":"getName","parameterTypes":[] }],
  "queriedMethods":[{"name":"getType","parameterTypes":[] }]
},
{
  "name":"name.ipsi.project.fwbp.foundry.DamageTypes",
  "allDeclaredFields":true,
  "queryAllDeclaredMethods":true
},
{
  "name":"name.ipsi.project.fwbp.foundry.DocumentTypes",
  "allDeclaredFields":true,
  "queryAllDeclaredMethods":true
},
{
  "name":"name.ipsi.project.fwbp.foundry.FoundryDocument",
  "queryAllDeclaredMethods":true
},
{
  "name":"name.ipsi.project.fwbp.foundry.GiftData",
  "allDeclaredFields":true,
  "queryAllDeclaredMethods":true,
  "queryAllDeclaredConstructors":true,
  "methods":[
    {"name":"getBonus","parameterTypes":[] }, 
    {"name":"getDescription","parameterTypes":[] }, 
    {"name":"getDice1","parameterTypes":[] }, 
    {"name":"getDice2","parameterTypes":[] }, 
    {"name":"getDifficulty","parameterTypes":[] }, 
    {"name":"getLevel","parameterTypes":[] }, 
    {"name":"getSystem","parameterTypes":[] }, 
    {"name":"getType","parameterTypes":[] }, 
    {"name":"getVersion","parameterTypes":[] }, 
    {"name":"getWorldAnvil","parameterTypes":[] }, 
    {"name":"isActive","parameterTypes":[] }, 
    {"name":"isCreated","parameterTypes":[] }, 
    {"name":"isIsRollable","parameterTypes":[] }, 
    {"name":"isIsactive","parameterTypes":[] }, 
    {"name":"isIscreated","parameterTypes":[] }, 
    {"name":"isRollable","parameterTypes":[] }
  ]
},
{
  "name":"name.ipsi.project.fwbp.foundry.Item",
  "allDeclaredFields":true,
  "queryAllDeclaredMethods":true,
  "queryAllDeclaredConstructors":true,
  "methods":[
    {"name":"getData","parameterTypes":[] }, 
    {"name":"getEffects","parameterTypes":[] }, 
    {"name":"getFlags","parameterTypes":[] }, 
    {"name":"getFolder","parameterTypes":[] }, 
    {"name":"getId","parameterTypes":[] }, 
    {"name":"getImg","parameterTypes":[] }, 
    {"name":"getName","parameterTypes":[] }, 
    {"name":"getPermission","parameterTypes":[] }, 
    {"name":"getSort","parameterTypes":[] }, 
    {"name":"getType","parameterTypes":[] }
  ]
},
{
  "name":"name.ipsi.project.fwbp.foundry.ItemData",
  "queryAllDeclaredMethods":true
},
{
  "name":"name.ipsi.project.fwbp.foundry.ItemTypes",
  "allDeclaredFields":true,
  "queryAllDeclaredMethods":true
},
{
  "name":"name.ipsi.project.fwbp.foundry.Journal",
  "allDeclaredFields":true,
  "queryAllDeclaredMethods":true,
  "queryAllDeclaredConstructors":true,
  "methods":[
    {"name":"getContent","parameterTypes":[] }, 
    {"name":"getFolder","parameterTypes":[] }, 
    {"name":"getId","parameterTypes":[] }, 
    {"name":"getName","parameterTypes":[] }
  ]
},
{
  "name":"name.ipsi.project.fwbp.foundry.MeleeWeaponData",
  "allDeclaredFields":true,
  "queryAllDeclaredMethods":true,
  "queryAllDeclaredConstructors":true,
  "methods":[
    {"name":"getAttack","parameterTypes":[] }, 
    {"name":"getConceal","parameterTypes":[] }, 
    {"name":"getDamage","parameterTypes":[] }, 
    {"name":"getDescription","parameterTypes":[] }, 
    {"name":"getDiff","parameterTypes":[] }, 
    {"name":"getDifficulty","parameterTypes":[] }, 
    {"name":"getLabel","parameterTypes":[] }, 
    {"name":"getVersion","parameterTypes":[] }, 
    {"name":"getWorldanvil","parameterTypes":[] }, 
    {"name":"isCreated","parameterTypes":[] }, 
    {"name":"isIsEquipped","parameterTypes":[] }, 
    {"name":"isIsMagical","parameterTypes":[] }, 
    {"name":"isIscreated","parameterTypes":[] }, 
    {"name":"isIstwohanded","parameterTypes":[] }, 
    {"name":"isNatural","parameterTypes":[] }, 
    {"name":"isTwohanded","parameterTypes":[] }
  ]
},
{
  "name":"name.ipsi.project.fwbp.foundry.MeleeWeaponData$Attack",
  "allDeclaredFields":true,
  "queryAllDeclaredMethods":true,
  "queryAllDeclaredConstructors":true,
  "methods":[
    {"name":"ability","parameterTypes":[] }, 
    {"name":"attribute","parameterTypes":[] }, 
    {"name":"isRollable","parameterTypes":[] }, 
    {"name":"roll","parameterTypes":[] }
  ]
},
{
  "name":"name.ipsi.project.fwbp.foundry.MeleeWeaponData$Damage",
  "allDeclaredFields":true,
  "queryAllDeclaredMethods":true,
  "queryAllDeclaredConstructors":true,
  "methods":[
    {"name":"attribute","parameterTypes":[] }, 
    {"name":"bonus","parameterTypes":[] }, 
    {"name":"isRollable","parameterTypes":[] }, 
    {"name":"roll","parameterTypes":[] }, 
    {"name":"type","parameterTypes":[] }
  ]
},
{
  "name":"name.ipsi.project.fwbp.foundry.Module",
  "allDeclaredFields":true,
  "queryAllDeclaredMethods":true,
  "queryAllDeclaredConstructors":true,
  "methods":[
    {"name":"getAuthor","parameterTypes":[] }, 
    {"name":"getCompatibleCoreVersion","parameterTypes":[] }, 
    {"name":"getDescription","parameterTypes":[] }, 
    {"name":"getMinimumCoreVersion","parameterTypes":[] }, 
    {"name":"getName","parameterTypes":[] }, 
    {"name":"getPacks","parameterTypes":[] }, 
    {"name":"getTitle","parameterTypes":[] }, 
    {"name":"getVersion","parameterTypes":[] }
  ]
},
{
  "name":"name.ipsi.project.fwbp.foundry.ModulePacks",
  "allDeclaredFields":true,
  "queryAllDeclaredMethods":true,
  "queryAllDeclaredConstructors":true,
  "methods":[
    {"name":"getLabel","parameterTypes":[] }, 
    {"name":"getModule","parameterTypes":[] }, 
    {"name":"getName","parameterTypes":[] }, 
    {"name":"getPath","parameterTypes":[] }, 
    {"name":"getType","parameterTypes":[] }
  ]
},
{
  "name":"name.ipsi.project.fwbp.foundry.PowerTypes",
  "allDeclaredFields":true,
  "queryAllDeclaredMethods":true
},
{
  "name":"name.ipsi.project.fwbp.foundry.WeaponConcealment",
  "allDeclaredFields":true,
  "queryAllDeclaredMethods":true
},
{
  "name":"sun.misc.Unsafe",
  "fields":[{"name":"theUnsafe"}],
  "queriedMethods":[{"name":"invokeCleaner","parameterTypes":["java.nio.ByteBuffer"] }]
}
]
